logicchunks/__init__.py
logicchunks/lists.py
tests/__init__.py
tests/test_operations.py
LogicChunks-0.1.0.dist-info/LICENSE
LogicChunks-0.1.0.dist-info/METADATA
LogicChunks-0.1.0.dist-info/WHEEL
LogicChunks-0.1.0.dist-info/top_level.txt
LogicChunks-0.1.0.dist-info/RECORD
