Metadata-Version: 2.1
Name: LogicChunks
Version: 0.1.0
Summary: A Python package to divide lists into groups based on conditions.
Home-page: https://github.com/yourusername/LogicChunks
Author: Manikanth Madishatti
Author-email: manikanthmadishatti4@gmail.com
License: MIT
Keywords: python,data structures,lists
Classifier: Programming Language :: Python :: 3
Classifier: License :: OSI Approved :: MIT License
Classifier: Operating System :: OS Independent
Requires-Python: >=3.6
License-File: LICENSE
